cabot_check_influxdb/__init__.py
cabot_check_influxdb/models.py
cabot_check_influxdb/urls.py
cabot_check_influxdb/views.py
cabot_check_influxdb/migrations/0001_initial.py
cabot_check_influxdb/migrations/__init__.py
cabot_check_influxdb-0.0.3.dist-info/DESCRIPTION.rst
cabot_check_influxdb-0.0.3.dist-info/METADATA
cabot_check_influxdb-0.0.3.dist-info/RECORD
cabot_check_influxdb-0.0.3.dist-info/WHEEL
cabot_check_influxdb-0.0.3.dist-info/metadata.json
cabot_check_influxdb-0.0.3.dist-info/top_level.txt
